[
    {
        "content": "verified email at liu.se - homepage  scholar. get my own ... a eklund, m andersson, c josephson, m johannesson, h knutsson. neuroimage 61 (3) ... a eklund, h ohlsson, m andersson, j rydell, a ynnerman, h knutsson. medical image...", 
        "email_addr_list": [
            "email@liu.se"
        ], 
        "cite_url": "scholar.google.com.sg/citations?user=x6pIxSEAAAAJhl=en", 
        "cite_name": "", 
        "title": "Anders Eklund - Google Scholar Citations"
    }, 
    {
        "content": "anders eklund. m.d. ph.d. professor ... unit: group j grunewald. e-mail: anders.eklund@ki.se ... unit: group j grunewald. e-mail: muntasir.abo.al.hayja@ki.se...", 
        "email_addr_list": [
            "anders.eklund@ki.se", 
            "muntasir.abo.al.hayja@ki.se"
        ], 
        "cite_url": "ki.se/en/meds/sarcoidosis", 
        "cite_name": "", 
        "title": "Sarcoidosis - Karolinska Institutet"
    }, 
    {
        "content": "onlinelibrary.wiley.com/doi/10.1002/bjs.5405/abstract. email: a. eklund (arne.eklund@ltv.se) * department of surgery, central hospital, 721 89 västerås,...", 
        "email_addr_list": [
            "arne.eklund@ltv.se"
        ], 
        "cite_url": "www.sogou.com/scholar?ie=utf8...Arne+Eklund...", 
        "cite_name": "", 
        "title": "Arne Eklund - 搜狗学术"
    }, 
    {
        "content": "nina.g.gustavsson@gmail.com ... johan-madde@bja.asplund.com. 15 ... mail. mobil. tränare. anders eklund anders.eklund@torpet.ac. 070-6290785. tränare.", 
        "email_addr_list": [
            "nina.g.gustavsson@gmail.com", 
            "johan-madde@bja.asplund.com", 
            "anders.eklund@torpet.ac"
        ], 
        "cite_url": "www.laget.se/SSKF06/Document/.../-1/4434745", 
        "cite_name": "", 
        "title": "[PDF]Mail-/Telefonlista - Laget.se"
    }
]