[
    {
        "content": "email: bdhammock@ucdavis.edu. fax: (530) 752-1537. bruce d. hammock, ph.d. - professor of entomology. hammock  prof. hammocks lab research.", 
        "email_addr_list": [
            "bdhammock@ucdavis.edu"
        ], 
        "cite_url": "entomology.ucdavis.edu/Faculty/Bruce_D_Hammock", 
        "cite_name": "", 
        "title": "Bruce D. Hammock - UC Davis Department of Entomology ..."
    }, 
    {
        "content": "jun 2, 2015 - hammock laboratory of pesticide biotechnology - research staff. ... candy_s. ph.d.: marine science, virginia institute of marine science b.s.: biological ... bruce d. hammock, pi ... webmaster email: alfchan@ucdavis.edu.", 
        "email_addr_list": [
            "alfchan@ucdavis.edu"
        ], 
        "cite_url": "www.biopestlab.ucdavis.edu/Our_People/Reseach_Staff", 
        "cite_name": "", 
        "title": "Research Staff - Hammock Laboratory of Pesticide ..."
    }, 
    {
        "content": "create alert. cancel. bruce d. hammock ... verified email at ucdavis.edu - homepage  scholar ... jd imig, x zhao, jh capdevila, c morisseau, bd hammock ... bf mccutchen, pv choudary, r crenshaw, d maddox, sg kamita, ... nature...", 
        "email_addr_list": [
            "email@ucdavis.edu"
        ], 
        "cite_url": "scholar.google.com/citations?user=GUeP1NIAAAAJhl=en", 
        "cite_name": "", 
        "title": "Bruce D. Hammock - Google Scholar Citations"
    }
]