[
    {
        "content": "email: carlo.napolitano@nyumc.org. publications. genetic modulators of the phenotype in the long qt syndrome: state of the art and clinical impact. napolitano...", 
        "email_addr_list": [
            "carlo.napolitano@nyumc.org"
        ], 
        "cite_url": "www.med.nyu.edu/biosketch/napolc01", 
        "cite_name": "", 
        "title": "Carlo Napolitano | NYU School of Medicine"
    }, 
    {
        "content": "email: spriori@fsm.it. clinical contact person: carlo napolitano, md, phd. tel: + 39 0382 592 050. fax: + 39 0382 592 094. email: cnapolitano@fsm.it...", 
        "email_addr_list": [
            "spriori@fsm.it", 
            "cnapolitano@fsm.it"
        ], 
        "cite_url": "www.eddnal.com/directory/detail.php?lab_id=409", 
        "cite_name": "", 
        "title": "Molecular Cardiology Laboratories - IRCCS ... - EDDNAL"
    }, 
    {
        "content": "carlonapolitano@hotmail.com is owned by carlo napolitano (roomviewa pty ltd). ... emails ... name, carlo napolitano, is associated with 5 domains.", 
        "email_addr_list": [
            "carlonapolitano@hotmail.com"
        ], 
        "cite_url": "domainbigdata.com/email/carlonapolitano@hotmail.com", 
        "cite_name": "", 
        "title": "Carlonapolitano@hotmail.com : Carlo Napolitano, Australia"
    }
]